{
  "updated_at": "2026-07-24T01:15:48.506663+09:00",
  "interval_hours": 1.0,
  "categories": [
    {
      "keyword": "축구",
      "items": [
        {
          "title": "축구協 개혁 속도전… 회장 선출 기한 연장",
          "description": "대한체육회가 2026 북중미월드컵 탈락 후 밀실 행정으로 질타를 받고 있는 대한축구협회의 개혁을 위한... 현재 축구협회는 정몽규 전 회장이 이달 초 사임하면서 이용수 부회장 직무대행 체제로 전환했다. 직무대행자가...",
          "link": "https://www.kmib.co.kr/article/view.asp?arcid=1784792711&code=12120000&cp=nv",
          "naver_link": "https://m.sports.naver.com/kfootball/article/005/0001862843",
          "pub_date": "Fri, 24 Jul 2026 01:10:00 +0900"
        },
        {
          "title": "‘AG 4연패 도전’ 이민성호, 중동강호들과 한 조… 사실상 죽음의 조",
          "description": "이민성 감독이 이끄는 남자 축구대표팀(U-23)은 23일 일본 나고야에서 열린 2026 아이치·나고야 아시안게임... 이번 대회 남자 축구는 총 15개 팀이 참가해 4개 조로 나뉘어 조별리그를 치른다. A~C조는 4개 팀이 경쟁하고...",
          "link": "https://www.kmib.co.kr/article/view.asp?arcid=1784794720&code=12120000&cp=nv",
          "naver_link": "https://m.sports.naver.com/kfootball/article/005/0001862842",
          "pub_date": "Fri, 24 Jul 2026 01:07:00 +0900"
        },
        {
          "title": "\"우리한테 세금 더 걷으세요\"…영국 부자 120명, 총리에 서한",
          "description": "버넘, 잇단 서민경제 활성화 정책…동네 펍 영업세 20% 인하 김지연 특파원 = 영화 '러브 액츄얼리'의 리처드 커티스 감독, 축구선수 출신 방송인 게리 리네커 등 영국 부자들이 앤디 버넘 총리에게 공개서한을 보내...",
          "link": "https://www.yna.co.kr/view/AKR20260724001100085?input=1195m",
          "naver_link": "https://n.news.naver.com/mnews/article/001/0016212145?sid=104",
          "pub_date": "Fri, 24 Jul 2026 01:05:00 +0900"
        },
        {
          "title": "중국, 한국 '역대급 꿀조'에 부러움 폭발! \"3팀 중 2팀 8강, 확실히 쉬운...",
          "description": "(U-23) 축구 대표팀이 2026 아이치·나고야 아시안게임에서 비교적 수월한 조에 편성됐다. 중국 매체 역시 한국이 속한 D조를 쉬운 조로 평가했다. 중국 '텐센트뉴스'는 23일(이하 한국시간) \"2026 아시안게임 남녀축구 조...",
          "link": "https://www.sportalkorea.com/news/articleView.html?idxno=2025052909553400911",
          "naver_link": "https://m.sports.naver.com/kfootball/article/139/0002250655",
          "pub_date": "Fri, 24 Jul 2026 01:02:00 +0900"
        },
        {
          "title": "\"SNS 뒤흔든 김민재\" 나폴리 '임대' 복귀설 급물살…伊매체 \"전혀 허황된...",
          "description": "튀르키예 축구 소식에 정통한 알리 나지 퀴취크 기자는 지난 18일 \"뮌헨이 이번 여름 김민재 이적료로 4000만 유로(약 671억 원)를 요구 중\"이라고 적었다. 축구 통계 사이트 트랜스퍼마크트 기준으로 현재 김민재...",
          "link": "https://www.spotvnews.co.kr/news/articleView.html?idxno=830317",
          "naver_link": "https://m.sports.naver.com/wfootball/article/477/0000619867",
          "pub_date": "Fri, 24 Jul 2026 00:54:00 +0900"
        },
        {
          "title": "주말 핫플된 ‘1호선 동묘앞’역",
          "description": "2번 출구로 나오면 프로축구팀 FC서울의 홈구장인 서울월드컵경기장과 바로 연결돼 주말마다 홈경기를 찾는 관중으로 붐빈다. 인원수로만 보면 2호선 홍대입구역의 증가 폭이 가장 컸다. 주말 하루에만 평일보다...",
          "link": "https://www.chosun.com/national/national_general/2026/07/24/DE6N5FDO25GGDG7HRIECMDQ3UY/?utm_source=naver&utm_medium=referral&utm_campaign=naver-news",
          "naver_link": "https://n.news.naver.com/mnews/article/023/0003989344?sid=102",
          "pub_date": "Fri, 24 Jul 2026 00:44:00 +0900"
        },
        {
          "title": "월드컵 끝나니 ‘흥’ 나네",
          "description": "손흥민, 美리그 2경기 연속골 10번째 도움까지… 팀도 3연승 MLS(미 프로축구) LA FC는 23일(한국 시각) 미국 LA BMO 스타디움에서 열린 솔트레이크시티와의 홈경기를 앞두고 관중에게 손흥민의 ‘찰칵 세리머니’를...",
          "link": "https://www.chosun.com/sports/world-football/2026/07/24/XNTC6GZBMNEVXFJGM7TC6X3RFQ/?utm_source=naver&utm_medium=referral&utm_campaign=naver-news",
          "naver_link": "https://m.sports.naver.com/wfootball/article/023/0003989336",
          "pub_date": "Fri, 24 Jul 2026 00:42:00 +0900"
        },
        {
          "title": "‘축구 神’ 메시가 19세 ‘신성’ 야말에게… “미래는 너희 세대 것, ...",
          "description": "‘축구의 신’ 리오넬 메시(39·아르헨티나)는 스페인에 0대1로 져 월드컵 2연패(連覇)가 무산되자 한동안... 야말은 “메시는 축구 역사상 최고의 선수”라며 “메시의 말은 제 목에 걸린 월드컵 우승 메달만큼이나 소중한...",
          "link": "https://www.chosun.com/national/people/2026/07/24/DOX6AD5RI5BJTEYZPJ7JZSQIWI/?utm_source=naver&utm_medium=referral&utm_campaign=naver-news",
          "naver_link": "https://n.news.naver.com/mnews/article/023/0003989324?sid=102",
          "pub_date": "Fri, 24 Jul 2026 00:39:00 +0900"
        },
        {
          "title": "\"한국 때문에 이강인 오피셜 지연\" AT 마드리드 한국 시장에 엄청난 기...",
          "description": "아틀레티코 마드리드는 이강인의 축구적인 역량보다 돈에 관심이 많은 것일까. 스페인 매체들은 계속해서... 축구 역량보다 수익을 더 기대하는 것이 아니냐는 의심이 들 정도다. 매체는 '이강인은 스포츠적 활약과 아시아...",
          "link": "https://www.sportschosun.com/football/2026-07-24/202607240100147300009366",
          "naver_link": "https://m.sports.naver.com/wfootball/article/076/0004428541",
          "pub_date": "Fri, 24 Jul 2026 00:36:00 +0900"
        },
        {
          "title": "[오피셜] 김지수·배준호·양민혁 등 韓 축구 미래들 운명 달린 AG 금메...",
          "description": "2026 아이치·나고야 아시안게임(AG) 금메달에 도전하는 한국 축구가에 ‘빨간불’이 켜졌다. 이민성 감독이... 2026 아시아축구연맹(AFC) 23세 이하(U-23) 아시안컵 성적(4위)에 따라 포트1을 받은 한국은 포트2에서 사우디...",
          "link": "https://www.goal.com/kr/뉴스/a/blt0cc1e948664dd478",
          "naver_link": "https://m.sports.naver.com/kfootball/article/216/0000141814",
          "pub_date": "Fri, 24 Jul 2026 00:36:00 +0900"
        }
      ]
    }
  ]
}