{
  "updated_at": "2026-06-29T23:37:26.207771+09:00",
  "interval_hours": 1.0,
  "categories": [
    {
      "keyword": "축구",
      "items": [
        {
          "title": "김종국, 단체로 축구 보다 말 잃었다…결과 떠난 진심 어린 응원 당부 ...",
          "description": "가수 김종국이 전 축구선수 전진우, 러블리즈 출신 정예인, 보디빌더 마선호와 함께 대한민국 축구 대표팀 경기를 시청하며 뜨거운 응원전을 펼쳤다. 김종국이 운영하는 유튜브 채널 '김종국 GYM JONG KOOK'에서는 '할말하않......",
          "link": "https://www.tenasia.co.kr/article/2026062951344",
          "naver_link": "https://m.entertain.naver.com/article/312/0000765701",
          "pub_date": "Mon, 29 Jun 2026 23:31:00 +0900"
        },
        {
          "title": "새 역사 쓰는 '축신' 메시…음바페·홀란드 맹추격",
          "description": "조별리그 전 경기에서 골 맛을 본 '축구의 신' 메시는 월드컵 통산 최다 득점 기록을 연이어 경신하며 자신의 한계를 뛰어넘고 있습니다. <리오넬 스칼로니 / 아르헨티나 감독(지난 27일)> \"메시는 기록에 연연하지...",
          "link": "http://www.yonhapnewstv.co.kr/news/MYH20260629232700eKJ",
          "naver_link": "https://n.news.naver.com/mnews/article/422/0000879700?sid=104",
          "pub_date": "Mon, 29 Jun 2026 23:27:00 +0900"
        },
        {
          "title": "\"I'm back!\" 외치고 바로 사라졌다...포를란 \"호날두가 포르투갈 월드컵...",
          "description": "축구 통계 매체 '풋몹'은 호날두에게 6.3점을 부여했는데, 이는 선발 출전한 선수들 중 가장 낮은 평점이었다. 포를란이 비판을 아끼지 않았다. 그는 'ESPN'에 출연해 \"문제는 호날두가 중앙에 버티고 있다는 점이다. 워낙...",
          "link": "https://www.interfootball.co.kr/news/articleView.html?idxno=689494",
          "naver_link": "https://m.sports.naver.com/worldcup2026/article/413/0000220178",
          "pub_date": "Mon, 29 Jun 2026 23:25:00 +0900"
        },
        {
          "title": "[공식발표]'충격! 첼시, 보상금 1700만파운드 받는다' 엔조 마레스카, 맨...",
          "description": "운영되는 축구 클럽이다. 그들이 하는 모든 일은 혁신적이고, 계획적이며, 목적이 분명하다. 감독에게... 나는 우리가 이기고, 좋은 축구를 구사하며, 맨시티를 대표한다는 압박감을 즐기기를 원한다\"고 덧붙였다....",
          "link": "https://www.sportschosun.com/football/2026-06-29/202606290100205130013498",
          "naver_link": "https://m.sports.naver.com/wfootball/article/076/0004420780",
          "pub_date": "Mon, 29 Jun 2026 23:25:00 +0900"
        },
        {
          "title": "곧 한국땅 밟는 홍명보 감독, 인천공항 경비 강화 태세…기동대와 공항...",
          "description": "대한민국 축구대표팀 지휘봉을 내려놓은 홍명보 전 감독을 향한 비판 여론이 극단적인 신변 위협으로까지 이어지면서 사법당국도 공항 입국장 경비 강화에 나섰다. 홍명보호는 2026 국제축구연맹(FIFA) 북중미 월드컵...",
          "link": "https://www.spotvnews.co.kr/news/articleView.html?idxno=825622",
          "naver_link": "https://m.sports.naver.com/worldcup2026/article/477/0000615954",
          "pub_date": "Mon, 29 Jun 2026 23:19:00 +0900"
        },
        {
          "title": "日 월드컵 감독은 고졸 비주류[횡설수설/장원재]",
          "description": "모리야스 하지메 일본 축구대표팀 감독은 축구 인생에서 가장 기억에 남는 일로 1993년 ‘도하의 비극’을 꼽는다. 미국 월드컵 최종예선 마지막 경기에서 종료 20초 전 이라크 선수가 동점골을 넣는 순간, 수비형...",
          "link": "https://www.donga.com/news/Opinion/article/all/20260629/134205347/2",
          "naver_link": "https://n.news.naver.com/mnews/article/020/0003730236?sid=110",
          "pub_date": "Mon, 29 Jun 2026 23:18:00 +0900"
        },
        {
          "title": "홍명보 감독, 월드컵 32강 진출 실패 책임 ‘사퇴’...이 대통령 \"조직과...",
          "description": "홍명보 대한민국 축구대표팀 감독이 2026 북중미 월드컵 32강 진출 실패의 책임을 지고 사퇴했습니다. 홍... 홍 감독은 이어 대한민국 축구를 향한 마음까지 내려놓은 것은 아니다라며 우리 대표팀이 다시 국민의 신뢰와...",
          "link": "https://www.voakorea.com/a/coach-hong-myung-bo-resigns-over-failure-to-advance-to-world-cup-round-of-32-062926/8166004.html",
          "naver_link": "https://www.voakorea.com/a/coach-hong-myung-bo-resigns-over-failure-to-advance-to-world-cup-round-of-32-062926/8166004.html",
          "pub_date": "Mon, 29 Jun 2026 23:13:00 +0900"
        },
        {
          "title": "[가천대 장세용 교수] 무지가 만든 패배, 카르텔이 키운 참사",
          "description": "최근 축구 대표팀을 둘러싼 비판 역시 본선 조별리그 탈락이라는 초라한 결과에서 비롯되었다. 그러나 결과만... 축구협회를 둘러싼 논란 역시 그 연장선에서 봐야 한다. 오늘의 패배는 우연이 아니라 구조가 만든 결과일...",
          "link": "https://www.upkoreanews.kr/news/articleView.html?idxno=99065",
          "naver_link": "https://www.upkoreanews.kr/news/articleView.html?idxno=99065",
          "pub_date": "Mon, 29 Jun 2026 23:11:00 +0900"
        },
        {
          "title": "'AI가 축구를 읽는다' 시각장애인 위한 음성중계, 뉴욕 광고제 파이널 ...",
          "description": "/한국프로축구연맹 제공 | 서울=한스경제 김성진 기자 | 재단법인 K리그어시스트와 하나금융그룹이 함께... 시각장애인 팬들은 전용 수신기를 이용해 현장에서 슈팅, 패스, 공격 전개 등 축구의 주요 장면을 생생하게...",
          "link": "http://www.hansbiz.co.kr/news/articleView.html?idxno=847150",
          "naver_link": "http://www.hansbiz.co.kr/news/articleView.html?idxno=847150",
          "pub_date": "Mon, 29 Jun 2026 23:06:00 +0900"
        },
        {
          "title": "이강인 마침내 'PSG 탈출' 확정! 아틀레티코행 '오피셜' 곧 뜬다...西 매...",
          "description": "대한민국 축구대표팀이 2026 국제축구연맹(FIFA) 북중미 월드컵 조별리그에서 탈락한 상황에서, 아틀레티코 마드리드가 이강인(PSG)의 영입 공식 발표를 앞두고 있다. 스페인 '마르카'는 29일(이하 한국시각) \"아틀레티코는...",
          "link": "https://www.mydaily.co.kr/page/view/2026062918265695793",
          "naver_link": "https://m.sports.naver.com/wfootball/article/117/0004079682",
          "pub_date": "Mon, 29 Jun 2026 23:05:00 +0900"
        }
      ]
    }
  ]
}